pdc/__init__.py
pdc/bqs.py
pdc/dp.py
py_ava-0.1.2.dist-info/LICENSE
py_ava-0.1.2.dist-info/METADATA
py_ava-0.1.2.dist-info/WHEEL
py_ava-0.1.2.dist-info/top_level.txt
py_ava-0.1.2.dist-info/RECORD
