Metadata-Version: 2.1
Name: py-ava
Version: 0.1.2
Summary: Automated Vehicle Architecture
Author: Jiri Vlasak
License: Copyright (c) 2022 Jiri Vlasak        
Project-URL: repository, https://git.sr.ht/~qeef/py-ava
Project-URL: documentation, https://py-ava.readthedocs.io
Project-URL: changelog, https://git.sr.ht/~qeef/py-ava/refs
License-File: LICENSE
